{"frames": {

"beach_land.png":
{
	"frame": {"x":16,"y":75,"w":16,"h":16},
	"rotated": false,
	"trimmed": false,
	"spriteSourceSize": {"x":0,"y":0,"w":16,"h":16},
	"sourceSize": {"w":16,"h":16}
},
"beach_plant.png":
{
	"frame": {"x":43,"y":12,"w":15,"h":14},
	"rotated": false,
	"trimmed": false,
	"spriteSourceSize": {"x":0,"y":0,"w":15,"h":14},
	"sourceSize": {"w":15,"h":14}
},
"beach_pond1.png":
{
	"frame": {"x":111,"y":107,"w":16,"h":16},
	"rotated": false,
	"trimmed": false,
	"spriteSourceSize": {"x":0,"y":0,"w":16,"h":16},
	"sourceSize": {"w":16,"h":16}
},
"beach_pond2.png":
{
	"frame": {"x":112,"y":91,"w":16,"h":16},
	"rotated": false,
	"trimmed": false,
	"spriteSourceSize": {"x":0,"y":0,"w":16,"h":16},
	"sourceSize": {"w":16,"h":16}
},
"beach_pond3.png":
{
	"frame": {"x":95,"y":107,"w":16,"h":16},
	"rotated": false,
	"trimmed": false,
	"spriteSourceSize": {"x":0,"y":0,"w":16,"h":16},
	"sourceSize": {"w":16,"h":16}
},
"beach_pond4.png":
{
	"frame": {"x":80,"y":91,"w":16,"h":16},
	"rotated": false,
	"trimmed": false,
	"spriteSourceSize": {"x":0,"y":0,"w":16,"h":16},
	"sourceSize": {"w":16,"h":16}
},
"beach_pond5.png":
{
	"frame": {"x":96,"y":91,"w":16,"h":16},
	"rotated": false,
	"trimmed": false,
	"spriteSourceSize": {"x":0,"y":0,"w":16,"h":16},
	"sourceSize": {"w":16,"h":16}
},
"beach_pond6.png":
{
	"frame": {"x":0,"y":107,"w":16,"h":16},
	"rotated": false,
	"trimmed": false,
	"spriteSourceSize": {"x":0,"y":0,"w":16,"h":16},
	"sourceSize": {"w":16,"h":16}
},
"beach_pond7.png":
{
	"frame": {"x":16,"y":107,"w":16,"h":16},
	"rotated": false,
	"trimmed": false,
	"spriteSourceSize": {"x":0,"y":0,"w":16,"h":16},
	"sourceSize": {"w":16,"h":16}
},
"beach_pond8.png":
{
	"frame": {"x":47,"y":107,"w":16,"h":16},
	"rotated": false,
	"trimmed": false,
	"spriteSourceSize": {"x":0,"y":0,"w":16,"h":16},
	"sourceSize": {"w":16,"h":16}
},
"beach_pond9.png":
{
	"frame": {"x":63,"y":107,"w":16,"h":16},
	"rotated": false,
	"trimmed": false,
	"spriteSourceSize": {"x":0,"y":0,"w":16,"h":16},
	"sourceSize": {"w":16,"h":16}
},
"beach_pond10.png":
{
	"frame": {"x":80,"y":75,"w":16,"h":16},
	"rotated": false,
	"trimmed": false,
	"spriteSourceSize": {"x":0,"y":0,"w":16,"h":16},
	"sourceSize": {"w":16,"h":16}
},
"beach_pond11.png":
{
	"frame": {"x":79,"y":107,"w":16,"h":16},
	"rotated": false,
	"trimmed": false,
	"spriteSourceSize": {"x":0,"y":0,"w":16,"h":16},
	"sourceSize": {"w":16,"h":16}
},
"beach_pond12.png":
{
	"frame": {"x":0,"y":91,"w":16,"h":16},
	"rotated": false,
	"trimmed": false,
	"spriteSourceSize": {"x":0,"y":0,"w":16,"h":16},
	"sourceSize": {"w":16,"h":16}
},
"beach_pond13.png":
{
	"frame": {"x":96,"y":75,"w":16,"h":16},
	"rotated": false,
	"trimmed": false,
	"spriteSourceSize": {"x":0,"y":0,"w":16,"h":16},
	"sourceSize": {"w":16,"h":16}
},
"beach_pond14.png":
{
	"frame": {"x":32,"y":75,"w":16,"h":16},
	"rotated": false,
	"trimmed": false,
	"spriteSourceSize": {"x":0,"y":0,"w":16,"h":16},
	"sourceSize": {"w":16,"h":16}
},
"beach_sprout.png":
{
	"frame": {"x":32,"y":107,"w":15,"h":16},
	"rotated": false,
	"trimmed": false,
	"spriteSourceSize": {"x":0,"y":0,"w":15,"h":16},
	"sourceSize": {"w":15,"h":16}
},
"blue_shell.png":
{
	"frame": {"x":28,"y":12,"w":15,"h":14},
	"rotated": false,
	"trimmed": false,
	"spriteSourceSize": {"x":0,"y":0,"w":15,"h":14},
	"sourceSize": {"w":15,"h":14}
},
"conch.png":
{
	"frame": {"x":73,"y":12,"w":14,"h":15},
	"rotated": false,
	"trimmed": false,
	"spriteSourceSize": {"x":0,"y":0,"w":14,"h":15},
	"sourceSize": {"w":14,"h":15}
},
"dead_animal.png":
{
	"frame": {"x":0,"y":153,"w":16,"h":31},
	"rotated": false,
	"trimmed": false,
	"spriteSourceSize": {"x":0,"y":0,"w":16,"h":31},
	"sourceSize": {"w":16,"h":31}
},
"desert_cliff.png":
{
	"frame": {"x":0,"y":0,"w":48,"h":12},
	"rotated": false,
	"trimmed": false,
	"spriteSourceSize": {"x":0,"y":0,"w":48,"h":12},
	"sourceSize": {"w":48,"h":12}
},
"desert_hill.png":
{
	"frame": {"x":80,"y":454,"w":44,"h":48},
	"rotated": false,
	"trimmed": false,
	"spriteSourceSize": {"x":0,"y":0,"w":44,"h":48},
	"sourceSize": {"w":44,"h":48}
},
"desert_land.png":
{
	"frame": {"x":64,"y":91,"w":16,"h":16},
	"rotated": false,
	"trimmed": false,
	"spriteSourceSize": {"x":0,"y":0,"w":16,"h":16},
	"sourceSize": {"w":16,"h":16}
},
"desert_pit.png":
{
	"frame": {"x":16,"y":153,"w":32,"h":32},
	"rotated": false,
	"trimmed": false,
	"spriteSourceSize": {"x":0,"y":0,"w":32,"h":32},
	"sourceSize": {"w":32,"h":32}
},
"dock_border.png":
{
	"frame": {"x":48,"y":75,"w":32,"h":16},
	"rotated": false,
	"trimmed": false,
	"spriteSourceSize": {"x":0,"y":0,"w":32,"h":16},
	"sourceSize": {"w":32,"h":16}
},
"fallen_tree.png":
{
	"frame": {"x":0,"y":27,"w":30,"h":15},
	"rotated": false,
	"trimmed": false,
	"spriteSourceSize": {"x":0,"y":0,"w":30,"h":15},
	"sourceSize": {"w":30,"h":15}
},
"flower_water_lily.png":
{
	"frame": {"x":0,"y":12,"w":14,"h":13},
	"rotated": false,
	"trimmed": false,
	"spriteSourceSize": {"x":0,"y":0,"w":14,"h":13},
	"sourceSize": {"w":14,"h":13}
},
"forest_cliff.png":
{
	"frame": {"x":80,"y":0,"w":48,"h":12},
	"rotated": false,
	"trimmed": false,
	"spriteSourceSize": {"x":0,"y":0,"w":48,"h":12},
	"sourceSize": {"w":48,"h":12}
},
"forest_fern.png":
{
	"frame": {"x":0,"y":123,"w":32,"h":21},
	"rotated": false,
	"trimmed": false,
	"spriteSourceSize": {"x":0,"y":0,"w":32,"h":21},
	"sourceSize": {"w":32,"h":21}
},
"forest_land.png":
{
	"frame": {"x":112,"y":75,"w":16,"h":16},
	"rotated": false,
	"trimmed": false,
	"spriteSourceSize": {"x":0,"y":0,"w":16,"h":16},
	"sourceSize": {"w":16,"h":16}
},
"forest_plant.png":
{
	"frame": {"x":16,"y":91,"w":16,"h":16},
	"rotated": false,
	"trimmed": false,
	"spriteSourceSize": {"x":0,"y":0,"w":16,"h":16},
	"sourceSize": {"w":16,"h":16}
},
"forest_small_plant.png":
{
	"frame": {"x":32,"y":91,"w":32,"h":16},
	"rotated": false,
	"trimmed": false,
	"spriteSourceSize": {"x":0,"y":0,"w":32,"h":16},
	"sourceSize": {"w":32,"h":16}
},
"forest_tree.png":
{
	"frame": {"x":40,"y":315,"w":40,"h":44},
	"rotated": false,
	"trimmed": false,
	"spriteSourceSize": {"x":0,"y":0,"w":40,"h":44},
	"sourceSize": {"w":40,"h":44}
},
"grass_land.png":
{
	"frame": {"x":48,"y":43,"w":16,"h":16},
	"rotated": false,
	"trimmed": false,
	"spriteSourceSize": {"x":0,"y":0,"w":16,"h":16},
	"sourceSize": {"w":16,"h":16}
},
"horizontal_dock.png":
{
	"frame": {"x":32,"y":454,"w":48,"h":48},
	"rotated": false,
	"trimmed": false,
	"spriteSourceSize": {"x":0,"y":0,"w":48,"h":48},
	"sourceSize": {"w":48,"h":48}
},
"large_cactus.png":
{
	"frame": {"x":32,"y":359,"w":28,"h":46},
	"rotated": false,
	"trimmed": false,
	"spriteSourceSize": {"x":0,"y":0,"w":28,"h":46},
	"sourceSize": {"w":28,"h":46}
},
"large_cut_tree.png":
{
	"frame": {"x":61,"y":123,"w":32,"h":29},
	"rotated": false,
	"trimmed": false,
	"spriteSourceSize": {"x":0,"y":0,"w":32,"h":29},
	"sourceSize": {"w":32,"h":29}
},
"medium_cactus.png":
{
	"frame": {"x":46,"y":123,"w":15,"h":26},
	"rotated": false,
	"trimmed": false,
	"spriteSourceSize": {"x":0,"y":0,"w":15,"h":26},
	"sourceSize": {"w":15,"h":26}
},
"palm_tree.png":
{
	"frame": {"x":80,"y":315,"w":36,"h":44},
	"rotated": false,
	"trimmed": false,
	"spriteSourceSize": {"x":0,"y":0,"w":36,"h":44},
	"sourceSize": {"w":36,"h":44}
},
"pipe.png":
{
	"frame": {"x":0,"y":406,"w":28,"h":47},
	"rotated": false,
	"trimmed": false,
	"spriteSourceSize": {"x":0,"y":0,"w":28,"h":47},
	"sourceSize": {"w":28,"h":47}
},
"player/down_1.png":
{
	"frame": {"x":30,"y":188,"w":30,"h":36},
	"rotated": false,
	"trimmed": false,
	"spriteSourceSize": {"x":0,"y":0,"w":30,"h":36},
	"sourceSize": {"w":30,"h":36}
},
"player/down_2.png":
{
	"frame": {"x":78,"y":153,"w":30,"h":35},
	"rotated": false,
	"trimmed": false,
	"spriteSourceSize": {"x":0,"y":0,"w":30,"h":35},
	"sourceSize": {"w":30,"h":35}
},
"player/down_3.png":
{
	"frame": {"x":0,"y":188,"w":30,"h":35},
	"rotated": false,
	"trimmed": false,
	"spriteSourceSize": {"x":0,"y":0,"w":30,"h":35},
	"sourceSize": {"w":30,"h":35}
},
"player/down_4.png":
{
	"frame": {"x":48,"y":153,"w":30,"h":34},
	"rotated": false,
	"trimmed": false,
	"spriteSourceSize": {"x":0,"y":0,"w":30,"h":34},
	"sourceSize": {"w":30,"h":34}
},
"player/left_1.png":
{
	"frame": {"x":27,"y":271,"w":27,"h":43},
	"rotated": false,
	"trimmed": false,
	"spriteSourceSize": {"x":0,"y":0,"w":27,"h":43},
	"sourceSize": {"w":27,"h":43}
},
"player/left_2.png":
{
	"frame": {"x":81,"y":229,"w":27,"h":42},
	"rotated": false,
	"trimmed": false,
	"spriteSourceSize": {"x":0,"y":0,"w":27,"h":42},
	"sourceSize": {"w":27,"h":42}
},
"player/left_3.png":
{
	"frame": {"x":54,"y":229,"w":27,"h":42},
	"rotated": false,
	"trimmed": false,
	"spriteSourceSize": {"x":0,"y":0,"w":27,"h":42},
	"sourceSize": {"w":27,"h":42}
},
"player/left_4.png":
{
	"frame": {"x":0,"y":229,"w":27,"h":41},
	"rotated": false,
	"trimmed": false,
	"spriteSourceSize": {"x":0,"y":0,"w":27,"h":41},
	"sourceSize": {"w":27,"h":41}
},
"player/right_1.png":
{
	"frame": {"x":54,"y":271,"w":27,"h":43},
	"rotated": false,
	"trimmed": false,
	"spriteSourceSize": {"x":0,"y":0,"w":27,"h":43},
	"sourceSize": {"w":27,"h":43}
},
"player/right_2.png":
{
	"frame": {"x":0,"y":271,"w":27,"h":42},
	"rotated": false,
	"trimmed": false,
	"spriteSourceSize": {"x":0,"y":0,"w":27,"h":42},
	"sourceSize": {"w":27,"h":42}
},
"player/right_3.png":
{
	"frame": {"x":27,"y":229,"w":27,"h":42},
	"rotated": false,
	"trimmed": false,
	"spriteSourceSize": {"x":0,"y":0,"w":27,"h":42},
	"sourceSize": {"w":27,"h":42}
},
"player/right_4.png":
{
	"frame": {"x":76,"y":188,"w":27,"h":41},
	"rotated": false,
	"trimmed": false,
	"spriteSourceSize": {"x":0,"y":0,"w":27,"h":41},
	"sourceSize": {"w":27,"h":41}
},
"player/up_1.png":
{
	"frame": {"x":0,"y":454,"w":32,"h":48},
	"rotated": false,
	"trimmed": false,
	"spriteSourceSize": {"x":0,"y":0,"w":32,"h":48},
	"sourceSize": {"w":32,"h":48}
},
"player/up_2.png":
{
	"frame": {"x":92,"y":359,"w":32,"h":47},
	"rotated": false,
	"trimmed": false,
	"spriteSourceSize": {"x":0,"y":0,"w":32,"h":47},
	"sourceSize": {"w":32,"h":47}
},
"player/up_3.png":
{
	"frame": {"x":60,"y":359,"w":32,"h":47},
	"rotated": false,
	"trimmed": false,
	"spriteSourceSize": {"x":0,"y":0,"w":32,"h":47},
	"sourceSize": {"w":32,"h":47}
},
"player/up_4.png":
{
	"frame": {"x":0,"y":359,"w":32,"h":46},
	"rotated": false,
	"trimmed": false,
	"spriteSourceSize": {"x":0,"y":0,"w":32,"h":46},
	"sourceSize": {"w":32,"h":46}
},
"pond.png":
{
	"frame": {"x":0,"y":502,"w":80,"h":48},
	"rotated": false,
	"trimmed": false,
	"spriteSourceSize": {"x":0,"y":0,"w":80,"h":48},
	"sourceSize": {"w":80,"h":48}
},
"sand_castle.png":
{
	"frame": {"x":87,"y":12,"w":14,"h":15},
	"rotated": false,
	"trimmed": false,
	"spriteSourceSize": {"x":0,"y":0,"w":14,"h":15},
	"sourceSize": {"w":14,"h":15}
},
"shell.png":
{
	"frame": {"x":58,"y":12,"w":15,"h":14},
	"rotated": false,
	"trimmed": false,
	"spriteSourceSize": {"x":0,"y":0,"w":15,"h":14},
	"sourceSize": {"w":15,"h":14}
},
"small_catus.png":
{
	"frame": {"x":78,"y":27,"w":16,"h":16},
	"rotated": false,
	"trimmed": false,
	"spriteSourceSize": {"x":0,"y":0,"w":16,"h":16},
	"sourceSize": {"w":16,"h":16}
},
"small_cut_tree.png":
{
	"frame": {"x":30,"y":27,"w":16,"h":15},
	"rotated": false,
	"trimmed": false,
	"spriteSourceSize": {"x":0,"y":0,"w":16,"h":15},
	"sourceSize": {"w":16,"h":15}
},
"snow_pile.png":
{
	"frame": {"x":93,"y":123,"w":32,"h":30},
	"rotated": false,
	"trimmed": false,
	"spriteSourceSize": {"x":0,"y":0,"w":32,"h":30},
	"sourceSize": {"w":32,"h":30}
},
"snowy_cliff.png":
{
	"frame": {"x":48,"y":0,"w":32,"h":12},
	"rotated": false,
	"trimmed": false,
	"spriteSourceSize": {"x":0,"y":0,"w":32,"h":12},
	"sourceSize": {"w":32,"h":12}
},
"snowy_grass.png":
{
	"frame": {"x":94,"y":27,"w":16,"h":16},
	"rotated": false,
	"trimmed": false,
	"spriteSourceSize": {"x":0,"y":0,"w":16,"h":16},
	"sourceSize": {"w":16,"h":16}
},
"snowy_hill.png":
{
	"frame": {"x":28,"y":406,"w":80,"h":48},
	"rotated": false,
	"trimmed": false,
	"spriteSourceSize": {"x":0,"y":0,"w":80,"h":48},
	"sourceSize": {"w":80,"h":48}
},
"snowy_land.png":
{
	"frame": {"x":62,"y":27,"w":16,"h":16},
	"rotated": false,
	"trimmed": false,
	"spriteSourceSize": {"x":0,"y":0,"w":16,"h":16},
	"sourceSize": {"w":16,"h":16}
},
"snowy_path1.png":
{
	"frame": {"x":110,"y":27,"w":16,"h":16},
	"rotated": false,
	"trimmed": false,
	"spriteSourceSize": {"x":0,"y":0,"w":16,"h":16},
	"sourceSize": {"w":16,"h":16}
},
"snowy_path2.png":
{
	"frame": {"x":0,"y":75,"w":16,"h":16},
	"rotated": false,
	"trimmed": false,
	"spriteSourceSize": {"x":0,"y":0,"w":16,"h":16},
	"sourceSize": {"w":16,"h":16}
},
"snowy_path3.png":
{
	"frame": {"x":96,"y":59,"w":16,"h":16},
	"rotated": false,
	"trimmed": false,
	"spriteSourceSize": {"x":0,"y":0,"w":16,"h":16},
	"sourceSize": {"w":16,"h":16}
},
"snowy_path4.png":
{
	"frame": {"x":112,"y":59,"w":16,"h":16},
	"rotated": false,
	"trimmed": false,
	"spriteSourceSize": {"x":0,"y":0,"w":16,"h":16},
	"sourceSize": {"w":16,"h":16}
},
"snowy_path5.png":
{
	"frame": {"x":64,"y":59,"w":16,"h":16},
	"rotated": false,
	"trimmed": false,
	"spriteSourceSize": {"x":0,"y":0,"w":16,"h":16},
	"sourceSize": {"w":16,"h":16}
},
"snowy_path6.png":
{
	"frame": {"x":16,"y":59,"w":16,"h":16},
	"rotated": false,
	"trimmed": false,
	"spriteSourceSize": {"x":0,"y":0,"w":16,"h":16},
	"sourceSize": {"w":16,"h":16}
},
"snowy_path7.png":
{
	"frame": {"x":16,"y":43,"w":16,"h":16},
	"rotated": false,
	"trimmed": false,
	"spriteSourceSize": {"x":0,"y":0,"w":16,"h":16},
	"sourceSize": {"w":16,"h":16}
},
"snowy_path8.png":
{
	"frame": {"x":32,"y":43,"w":16,"h":16},
	"rotated": false,
	"trimmed": false,
	"spriteSourceSize": {"x":0,"y":0,"w":16,"h":16},
	"sourceSize": {"w":16,"h":16}
},
"snowy_path9.png":
{
	"frame": {"x":64,"y":43,"w":16,"h":16},
	"rotated": false,
	"trimmed": false,
	"spriteSourceSize": {"x":0,"y":0,"w":16,"h":16},
	"sourceSize": {"w":16,"h":16}
},
"snowy_path10.png":
{
	"frame": {"x":46,"y":27,"w":16,"h":16},
	"rotated": false,
	"trimmed": false,
	"spriteSourceSize": {"x":0,"y":0,"w":16,"h":16},
	"sourceSize": {"w":16,"h":16}
},
"snowy_path11.png":
{
	"frame": {"x":0,"y":43,"w":16,"h":16},
	"rotated": false,
	"trimmed": false,
	"spriteSourceSize": {"x":0,"y":0,"w":16,"h":16},
	"sourceSize": {"w":16,"h":16}
},
"snowy_path12.png":
{
	"frame": {"x":32,"y":59,"w":16,"h":16},
	"rotated": false,
	"trimmed": false,
	"spriteSourceSize": {"x":0,"y":0,"w":16,"h":16},
	"sourceSize": {"w":16,"h":16}
},
"snowy_path13.png":
{
	"frame": {"x":48,"y":59,"w":16,"h":16},
	"rotated": false,
	"trimmed": false,
	"spriteSourceSize": {"x":0,"y":0,"w":16,"h":16},
	"sourceSize": {"w":16,"h":16}
},
"snowy_path14.png":
{
	"frame": {"x":80,"y":59,"w":16,"h":16},
	"rotated": false,
	"trimmed": false,
	"spriteSourceSize": {"x":0,"y":0,"w":16,"h":16},
	"sourceSize": {"w":16,"h":16}
},
"snowy_plant.png":
{
	"frame": {"x":0,"y":59,"w":16,"h":16},
	"rotated": false,
	"trimmed": false,
	"spriteSourceSize": {"x":0,"y":0,"w":16,"h":16},
	"sourceSize": {"w":16,"h":16}
},
"snowy_small_plant.png":
{
	"frame": {"x":80,"y":43,"w":16,"h":16},
	"rotated": false,
	"trimmed": false,
	"spriteSourceSize": {"x":0,"y":0,"w":16,"h":16},
	"sourceSize": {"w":16,"h":16}
},
"snowy_sprout.png":
{
	"frame": {"x":32,"y":123,"w":14,"h":24},
	"rotated": false,
	"trimmed": false,
	"spriteSourceSize": {"x":0,"y":0,"w":14,"h":24},
	"sourceSize": {"w":14,"h":24}
},
"snowy_tree.png":
{
	"frame": {"x":0,"y":315,"w":40,"h":44},
	"rotated": false,
	"trimmed": false,
	"spriteSourceSize": {"x":0,"y":0,"w":40,"h":44},
	"sourceSize": {"w":40,"h":44}
},
"swamp_plant.png":
{
	"frame": {"x":60,"y":188,"w":16,"h":39},
	"rotated": false,
	"trimmed": false,
	"spriteSourceSize": {"x":0,"y":0,"w":16,"h":39},
	"sourceSize": {"w":16,"h":39}
},
"swamp_tree.png":
{
	"frame": {"x":81,"y":271,"w":36,"h":44},
	"rotated": false,
	"trimmed": false,
	"spriteSourceSize": {"x":0,"y":0,"w":36,"h":44},
	"sourceSize": {"w":36,"h":44}
},
"vertical_dock.png":
{
	"frame": {"x":96,"y":43,"w":32,"h":16},
	"rotated": false,
	"trimmed": false,
	"spriteSourceSize": {"x":0,"y":0,"w":32,"h":16},
	"sourceSize": {"w":32,"h":16}
},
"water_lily.png":
{
	"frame": {"x":14,"y":12,"w":14,"h":13},
	"rotated": false,
	"trimmed": false,
	"spriteSourceSize": {"x":0,"y":0,"w":14,"h":13},
	"sourceSize": {"w":14,"h":13}
}},
"meta": {
	"app": "http://www.codeandweb.com/texturepacker",
	"version": "1.0",
	"image": "map-tiles.png",
	"format": "RGBA8888",
	"size": {"w":128,"h":550},
	"scale": "1",
	"smartupdate": "$TexturePacker:SmartUpdate:d0b7084e7a7e787543bb931b9facaaa6:efc7a3651a37f0173073364ee083648d:e1681c6011e5b21fafa27c079e232ca4$"
}
}
